{
    "AX": {
        "error": 0.00890597328543663,
        "error_type": null,
        "filter_outliers_dict": {
            "filter_outliers": true,
            "iterations": 1,
            "std_devs": 2,
            "use_iqr_filtering": false,
            "use_standard_deviation_filtering": false
        },
        "fit": "average",
        "fn": 0,
        "include_baseline_error": false,
        "n": 0,
        "outlier_excluded": null,
        "reviewed": false,
        "user_excluded": null,
        "value": 0.04309982369229866
    },
    "CDD": {
        "error": 5.2384268201421946e-05,
        "error_type": null,
        "filter_outliers_dict": {
            "filter_outliers": true,
            "iterations": 1,
            "std_devs": 10,
            "use_iqr_filtering": false,
            "use_standard_deviation_filtering": false
        },
        "fit": "average",
        "fn": 0,
        "include_baseline_error": false,
        "n": 0,
        "outlier_excluded": null,
        "reviewed": false,
        "user_excluded": null,
        "value": 0.00048062393745925975
    },
    "H1": {
        "error": 0.00852998811751604,
        "error_type": null,
        "filter_outliers_dict": {
            "filter_outliers": true,
            "iterations": 1,
            "std_devs": 2,
            "use_iqr_filtering": false,
            "use_standard_deviation_filtering": false
        },
        "fit": "average",
        "fn": 0,
        "include_baseline_error": false,
        "n": 0,
        "outlier_excluded": null,
        "reviewed": false,
        "user_excluded": null,
        "value": 0.08737495628858054
    },
    "H2": {
        "error": 0.05138077586889267,
        "error_type": null,
        "filter_outliers_dict": {
            "filter_outliers": true,
            "iterations": 1,
            "std_devs": 2,
            "use_iqr_filtering": false,
            "use_standard_deviation_filtering": false
        },
        "fit": "average",
        "fn": 0,
        "include_baseline_error": false,
        "n": 0,
        "outlier_excluded": null,
        "reviewed": false,
        "user_excluded": null,
        "value": -0.45445064839009686
    },
    "L1": {
        "error": 0.0038151582702994347,
        "error_type": null,
        "filter_outliers_dict": {
            "filter_outliers": true,
            "iterations": 1,
            "std_devs": 2,
            "use_iqr_filtering": false,
            "use_standard_deviation_filtering": false
        },
        "fit": "average",
        "fn": 0,
        "include_baseline_error": false,
        "n": 0,
        "outlier_excluded": null,
        "reviewed": false,
        "user_excluded": null,
        "value": 0.03243837416160542
    },
    "L2": {
        "error": 0.0048358263447880745,
        "error_type": null,
        "filter_outliers_dict": {
            "filter_outliers": true,
            "iterations": 1,
            "std_devs": 2,
            "use_iqr_filtering": false,
            "use_standard_deviation_filtering": false
        },
        "fit": "average",
        "fn": 0,
        "include_baseline_error": false,
        "n": 0,
        "outlier_excluded": null,
        "reviewed": false,
        "user_excluded": null,
        "value": -0.038605161760041556
    }
}