{
    "Ar36": {
        "error": 0.00073456635354996,
        "error_type": "SEM",
        "filter_outliers_dict": {
            "filter_outliers": true,
            "iterations": 1,
            "std_devs": 2,
            "use_iqr_filtering": false,
            "use_standard_deviation_filtering": false
        },
        "fit": "Parabolic",
        "fn": 265,
        "include_baseline_error": false,
        "n": 280,
        "outlier_excluded": [
            2,
            162,
            247,
            270,
            111,
            176,
            177,
            178,
            207,
            84,
            209,
            183,
            91,
            252,
            157
        ],
        "reviewed": true,
        "user_excluded": [],
        "value": 0.08754993149144491
    },
    "Ar37": {
        "error": 0.003932162643753324,
        "error_type": "SEM",
        "filter_outliers_dict": {
            "filter_outliers": true,
            "iterations": 1,
            "std_devs": 2,
            "use_iqr_filtering": false,
            "use_standard_deviation_filtering": false
        },
        "fit": "Linear",
        "fn": 270,
        "include_baseline_error": false,
        "n": 280,
        "outlier_excluded": [
            193,
            71,
            171,
            207,
            20,
            119,
            276,
            151,
            121,
            157
        ],
        "reviewed": true,
        "user_excluded": [],
        "value": 1.3802686106485935
    },
    "Ar38": {
        "error": 0.0038341013400888108,
        "error_type": "SEM",
        "filter_outliers_dict": {
            "filter_outliers": true,
            "iterations": 1,
            "std_devs": 2,
            "use_iqr_filtering": false,
            "use_standard_deviation_filtering": false
        },
        "fit": "Linear",
        "fn": 266,
        "include_baseline_error": false,
        "n": 280,
        "outlier_excluded": [
            131,
            39,
            71,
            73,
            107,
            44,
            18,
            19,
            114,
            54,
            119,
            120,
            249,
            216
        ],
        "reviewed": true,
        "user_excluded": [],
        "value": 6.2682239714639145
    },
    "Ar39": {
        "error": 0.045850950468611915,
        "error_type": "SEM",
        "filter_outliers_dict": {
            "filter_outliers": true,
            "iterations": 1,
            "std_devs": 2,
            "use_iqr_filtering": false,
            "use_standard_deviation_filtering": false
        },
        "fit": "Parabolic",
        "fn": 266,
        "include_baseline_error": false,
        "n": 280,
        "outlier_excluded": [
            65,
            66,
            259,
            70,
            166,
            136,
            43,
            237,
            111,
            115,
            116,
            185,
            124,
            62
        ],
        "reviewed": true,
        "user_excluded": [],
        "value": 524.86867511223
    },
    "Ar40": {
        "error": 0.095161565756627,
        "error_type": "SEM",
        "filter_outliers_dict": {
            "filter_outliers": true,
            "iterations": 1,
            "std_devs": 2,
            "use_iqr_filtering": false,
            "use_standard_deviation_filtering": false
        },
        "fit": "Parabolic",
        "fn": 267,
        "include_baseline_error": false,
        "n": 280,
        "outlier_excluded": [
            1,
            197,
            198,
            264,
            234,
            174,
            175,
            48,
            176,
            272,
            20,
            61,
            62
        ],
        "reviewed": true,
        "user_excluded": [],
        "value": 2154.529270502723
    },
    "Ar41": {
        "error": 0.05364857772486748,
        "error_type": "SEM",
        "filter_outliers_dict": {
            "filter_outliers": true,
            "iterations": 1,
            "std_devs": 2,
            "use_iqr_filtering": false,
            "use_standard_deviation_filtering": false
        },
        "fit": "linear",
        "fn": 0,
        "include_baseline_error": false,
        "n": 0,
        "outlier_excluded": null,
        "reviewed": false,
        "user_excluded": null,
        "value": -0.29638643459145214
    }
}